feign/__init__.py
feign-0.42.dist-info/METADATA
feign-0.42.dist-info/WHEEL
feign-0.42.dist-info/top_level.txt
feign-0.42.dist-info/RECORD
