Metadata-Version: 2.1
Name: feign
Version: 0.42
Summary: Feign a function signature
Author-email: Kosio Karchev <kosiokarchev@gmail.com>
License: GPLv3
Classifier: License :: OSI Approved :: GNU General Public License v3 (GPLv3)
Classifier: Programming Language :: Python :: 3
